pyloves/__init__.py
pyloves/pyloves.py
pyloves-1.0.0.dist-info/AUTHORS.rst
pyloves-1.0.0.dist-info/LICENSE
pyloves-1.0.0.dist-info/METADATA
pyloves-1.0.0.dist-info/WHEEL
pyloves-1.0.0.dist-info/top_level.txt
pyloves-1.0.0.dist-info/RECORD
