Metadata-Version: 2.1
Name: pyloves
Version: 1.0.0
Summary: Pyloveis a python library create to show all my love and creativity to Sara Maria Bejarano the love of my live
Home-page: https://github.com/jsprieto10/pyloves
Author: juan sebastian prieto
Author-email: js.prieto10@uniandes.edu.co
License: MIT license
Keywords: pyloves
Platform: UNKNOWN
Classifier: Development Status :: 2 - Pre-Alpha
Classifier: Intended Audience :: Developers
Classifier: License :: OSI Approved :: MIT License
Classifier: Natural Language :: English
Classifier: Programming Language :: Python :: 3
Classifier: Programming Language :: Python :: 3.5
Classifier: Programming Language :: Python :: 3.6
Classifier: Programming Language :: Python :: 3.7
Classifier: Programming Language :: Python :: 3.8
Requires-Python: >=3.5
Requires-Dist: cryptography
Requires-Dist: googletrans
